git_cloner/__init__.py
git_cloner/git_cloner.py
django_sekai-0.2.4.dist-info/METADATA
django_sekai-0.2.4.dist-info/WHEEL
django_sekai-0.2.4.dist-info/entry_points.txt
django_sekai-0.2.4.dist-info/top_level.txt
django_sekai-0.2.4.dist-info/RECORD
